{
  "themes": [
    {
      "id": "2024-05-19T15:33:51.236Z",
      "name": "Tema Azul Claro",
      "colors": {
        "primary": "#084a91",
        "secondary": "#6c757d",
        "success": "#28a745",
        "danger": "#dc3545",
        "warning": "#ffc107"
      }
    },
    {
      "id": "2024-05-19T16:21:08.587Z",
      "name": "Tema Roxo",
      "colors": {
        "primary": "#7b62f9",
        "secondary": "#6c757d",
        "success": "#28a745",
        "danger": "#dc3545",
        "warning": "#ffc107"
      }
    }
  ]
}